{"entregasBase":[{"NumeroSequencial":"1","CodigoConsultora":"27801209","Previsao":"13 a 14","Nome":"FLAVIA DANIELLE MAFRA COMISSO","Rota":"0008","Semana":"","Observacao":""},{"NumeroSequencial":"2","CodigoConsultora":"27721685","Previsao":"13 a 14","Nome":"TALITA CAVALHERI DA SILVA","Rota":"0008","Semana":"","Observacao":""},{"NumeroSequencial":"3","CodigoConsultora":"30093760","Previsao":"13 a 14","Nome":"SUSILENE LETTY","Rota":"0008","Semana":"","Observacao":""},{"NumeroSequencial":"4","CodigoConsultora":"30053181","Previsao":"13 a 14","Nome":"KATIA DE OLIVEIRA BRITO","Rota":"0008","Semana":"","Observacao":""},{"NumeroSequencial":"5","CodigoConsultora":"30011090","Previsao":"13 a 14","Nome":"IVAN SALVADOR DOS SANTOS","Rota":"0008","Semana":"","Observacao":""},{"NumeroSequencial":"6","CodigoConsultora":"30091083","Previsao":"13 a 14","Nome":"JULIA SOUZA OLIVEIRA SILVA","Rota":"0008","Semana":"","Observacao":""},{"NumeroSequencial":"7","CodigoConsultora":"27719224","Previsao":"13 a 14","Nome":"GABRIEL DOS SANTOS PINHEIRO","Rota":"0008","Semana":"","Observacao":""},{"NumeroSequencial":"8","CodigoConsultora":"30088035","Previsao":"13 a 14","Nome":"GABRIELLE PIMENTEL OLIVEIRA","Rota":"0008","Semana":"","Observacao":""},{"NumeroSequencial":"9","CodigoConsultora":"30157214","Previsao":"13 a 14","Nome":"KAUANY VYTORYA MARIANO","Rota":"0008","Semana":"","Observacao":""},{"NumeroSequencial":"10","CodigoConsultora":"30023232","Previsao":"13 a 14","Nome":"PAULA CRISTINA TONCHE DA SILVA","Rota":"0008","Semana":"","Observacao":""},{"NumeroSequencial":"11","CodigoConsultora":"30146693","Previsao":"13 a 14","Nome":"GISELE CRISTINA GRACA GUBERTONI","Rota":"0008","Semana":"","Observacao":""},{"NumeroSequencial":"12","CodigoConsultora":"30086739","Previsao":"13 a 14","Nome":"ALEXANDRE ANTONIO FELIX DOMINGUES JUNIOR","Rota":"0008","Semana":"","Observacao":""},{"NumeroSequencial":"13","CodigoConsultora":"30081322","Previsao":"13 a 14","Nome":"CAMILA MACHADO","Rota":"0008","Semana":"","Observacao":""},{"NumeroSequencial":"14","CodigoConsultora":"27061940","Previsao":"13 a 14","Nome":"MARIA KEYLA SOUZA RODRIGUES","Rota":"0010","Semana":"","Observacao":""},{"NumeroSequencial":"15","CodigoConsultora":"30007838","Previsao":"13 a 14","Nome":"VANESSA ALVES BEZERRA DA SILVA","Rota":"0010","Semana":"","Observacao":""},{"NumeroSequencial":"16","CodigoConsultora":"30016344","Previsao":"13 a 14","Nome":"DANIELA CASTRIANI DE ANDRADE","Rota":"0010","Semana":"","Observacao":""},{"NumeroSequencial":"17","CodigoConsultora":"30152559","Previsao":"13 a 14","Nome":"ANTONIO RODRIGUES","Rota":"0010","Semana":"","Observacao":""},{"NumeroSequencial":"18","CodigoConsultora":"27587797","Previsao":"13 a 14","Nome":"DEBORA ALDES DE MORAES","Rota":"0010","Semana":"","Observacao":""},{"NumeroSequencial":"19","CodigoConsultora":"30020152","Previsao":"13 a 14","Nome":"ELAINE CRISTINA DA SILVA","Rota":"0010","Semana":"","Observacao":""},{"NumeroSequencial":"20","CodigoConsultora":"30010032","Previsao":"13 a 14","Nome":"GABRIELLE PALMIERI CUNHA","Rota":"0010","Semana":"","Observacao":""},{"NumeroSequencial":"21","CodigoConsultora":"30014752","Previsao":"13 a 14","Nome":"RENATA PRISCILA MANOEL MARTINS","Rota":"0010","Semana":"","Observacao":""},{"NumeroSequencial":"22","CodigoConsultora":"27722659","Previsao":"13 a 14","Nome":"JOSYMARA DE OLIVEIRA DOS SANTOS","Rota":"0010","Semana":"","Observacao":""},{"NumeroSequencial":"23","CodigoConsultora":"27723554","Previsao":"13 a 14","Nome":"JULIANO ERIC MARTINS DOS SANTOS","Rota":"0010","Semana":"","Observacao":""},{"NumeroSequencial":"24","CodigoConsultora":"30139097","Previsao":"13 a 14","Nome":"REBECA BRUNELLI DE OLIVEIRA","Rota":"0010","Semana":"","Observacao":""},{"NumeroSequencial":"25","CodigoConsultora":"30009208","Previsao":"13 a 14","Nome":"JULIANA FERREIRA MACHADO","Rota":"0010","Semana":"","Observacao":""},{"NumeroSequencial":"26","CodigoConsultora":"27725040","Previsao":"13 a 14","Nome":"JAQUELINE CRISTINA DA SILVA MARCONDES","Rota":"0010","Semana":"","Observacao":""},{"NumeroSequencial":"27","CodigoConsultora":"30005025","Previsao":"13 a 14","Nome":"KATIA CINDI ANTUNES FARIA","Rota":"0010","Semana":"","Observacao":""},{"NumeroSequencial":"28","CodigoConsultora":"27502279","Previsao":"13 a 14","Nome":"NAJARA BRASIL DOS SANTOS","Rota":"0010","Semana":"","Observacao":""},{"NumeroSequencial":"29","CodigoConsultora":"30032731","Previsao":"13 a 14","Nome":"ROBERTA DOS SANTOS LUGUEZI","Rota":"0010","Semana":"","Observacao":""},{"NumeroSequencial":"30","CodigoConsultora":"27587819","Previsao":"13 a 14","Nome":"ROSANA CLEMENTE LEMES","Rota":"0010","Semana":"","Observacao":""},{"NumeroSequencial":"31","CodigoConsultora":"27725827","Previsao":"13 a 14","Nome":"MARIANA AUGUSTA DE FREITAS","Rota":"0010","Semana":"","Observacao":""},{"NumeroSequencial":"32","CodigoConsultora":"27018748","Previsao":"13 a 14","Nome":"ANA CARLA SILVA BRITO","Rota":"0010","Semana":"","Observacao":""},{"NumeroSequencial":"33","CodigoConsultora":"30065807","Previsao":"13 a 14","Nome":"CINTIA VIEIRA RODRIGUES DOS SANTOS","Rota":"0010","Semana":"","Observacao":""},{"NumeroSequencial":"34","CodigoConsultora":"27282647","Previsao":"13 a 14","Nome":"JESSICA CAROLINE DA SILVA ANTUNES ANTUNES","Rota":"0010","Semana":"","Observacao":""},{"NumeroSequencial":"35","CodigoConsultora":"27389583","Previsao":"13 a 14","Nome":"ELIETE PEREIRA DA SILVA SILVA","Rota":"0010","Semana":"","Observacao":""},{"NumeroSequencial":"36","CodigoConsultora":"27281348","Previsao":"13 a 14","Nome":"KATIA CRISTINA M RODRIGUES","Rota":"0010","Semana":"","Observacao":""},{"NumeroSequencial":"37","CodigoConsultora":"27009376","Previsao":"13 a 14","Nome":"ZENICE FIGUEIRA","Rota":"0010","Semana":"","Observacao":""},{"NumeroSequencial":"38","CodigoConsultora":"30014248","Previsao":"13 a 14","Nome":"ELIZETE MENDES  BARBOSA BERTONI","Rota":"0010","Semana":"","Observacao":""},{"NumeroSequencial":"39","CodigoConsultora":"30145591","Previsao":"13 a 14","Nome":"ALINE SATURNINO DA SILVA MORAES","Rota":"0010","Semana":"","Observacao":""},{"NumeroSequencial":"40","CodigoConsultora":"27008932","Previsao":"13 a 14","Nome":"ANTONIA ANTONIETA CAVALCANTE MAIA","Rota":"0010","Semana":"","Observacao":""},{"NumeroSequencial":"41","CodigoConsultora":"27057576","Previsao":"13 a 14","Nome":"VALDA FERREIRA LIMA ROCHA","Rota":"0010","Semana":"","Observacao":""},{"NumeroSequencial":"42","CodigoConsultora":"27259311","Previsao":"13 a 14","Nome":"ALCINA REGINA DANTAS PAVANETE","Rota":"0010","Semana":"","Observacao":""},{"NumeroSequencial":"43","CodigoConsultora":"27260808","Previsao":"13 a 14","Nome":"DAIANA FERNANDA DOS SANTOS","Rota":"0010","Semana":"","Observacao":""},{"NumeroSequencial":"44","CodigoConsultora":"27800587","Previsao":"13 a 14","Nome":"JULIANA GONCALVES DA COSTA","Rota":"0010","Semana":"","Observacao":""},{"NumeroSequencial":"45","CodigoConsultora":"30114173","Previsao":"13 a 14","Nome":"FABIA REGINA DE GODOI SOUZA","Rota":"0010","Semana":"","Observacao":""},{"NumeroSequencial":"46","CodigoConsultora":"30141654","Previsao":"13 a 14","Nome":"ALEX DE SOUZA FGUEIRA","Rota":"0010","Semana":"","Observacao":""},{"NumeroSequencial":"47","CodigoConsultora":"30096446","Previsao":"13 a 14","Nome":"MORGANA RAMOS DE ARUJO","Rota":"0010","Semana":"","Observacao":""},{"NumeroSequencial":"48","CodigoConsultora":"27254006","Previsao":"13 a 14","Nome":"SOLANGE DE ALMEIDA PEREIRA","Rota":"0010","Semana":"","Observacao":""},{"NumeroSequencial":"49","CodigoConsultora":"30149600","Previsao":"13 a 14","Nome":"MARIA WANDERLUCIA DOS SANTOS FERREIRA","Rota":"0010","Semana":"","Observacao":""},{"NumeroSequencial":"50","CodigoConsultora":"27714239","Previsao":"13 a 14","Nome":"DIEGO FAGUNDES PEREIRA","Rota":"0010","Semana":"","Observacao":""},{"NumeroSequencial":"51","CodigoConsultora":"30011738","Previsao":"13 a 14","Nome":"FILIPI SAMUEL DA SILVA","Rota":"0010","Semana":"","Observacao":""},{"NumeroSequencial":"52","CodigoConsultora":"27331880","Previsao":"13 a 14","Nome":"MAGDA PENA MARTINS","Rota":"0010","Semana":"","Observacao":""},{"NumeroSequencial":"53","CodigoConsultora":"27726066","Previsao":"13 a 14","Nome":"MARIA APARECIDA ALKIMIM DOS SANTOS","Rota":"0010","Semana":"","Observacao":""},{"NumeroSequencial":"54","CodigoConsultora":"27401957","Previsao":"13 a 14","Nome":"VANESSA MACHADO","Rota":"0010","Semana":"","Observacao":""},{"NumeroSequencial":"55","CodigoConsultora":"30112920","Previsao":"11 de outubro","Nome":"KAILAN NUNES NOVAIS","Rota":"0019","Semana":"","Observacao":""},{"NumeroSequencial":"56","CodigoConsultora":"30043757","Previsao":"11 de outubro","Nome":"MARIA CLEUSA DA SILVA MENDES","Rota":"0019","Semana":"","Observacao":""},{"NumeroSequencial":"57","CodigoConsultora":"27801010","Previsao":"11 de outubro","Nome":"MARIA LUCIA MENEGASSI MASSA","Rota":"0019","Semana":"","Observacao":""},{"NumeroSequencial":"58","CodigoConsultora":"27514742","Previsao":"11 de outubro","Nome":"CLAUDIA PAIVA SANTOS SILVA","Rota":"0019","Semana":"","Observacao":""},{"NumeroSequencial":"59","CodigoConsultora":"30121326","Previsao":"11 de outubro","Nome":"TALITA FIORINI MAYER DE OLIVEIRA","Rota":"0019","Semana":"","Observacao":""},{"NumeroSequencial":"60","CodigoConsultora":"30009123","Previsao":"11 de outubro","Nome":"VANESSA GONCALVES DIAS","Rota":"0019","Semana":"","Observacao":""},{"NumeroSequencial":"61","CodigoConsultora":"30107201","Previsao":"11 de outubro","Nome":"MELRE RELP DE MACENA PASSOS","Rota":"0019","Semana":"","Observacao":""},{"NumeroSequencial":"62","CodigoConsultora":"27612095","Previsao":"11 de outubro","Nome":"ROSA FRANCISCA DE CARVALHO","Rota":"0019","Semana":"","Observacao":""},{"NumeroSequencial":"63","CodigoConsultora":"30006691","Previsao":"11 de outubro","Nome":"NELI ROMANO DE MELLO SOUSA","Rota":"0019","Semana":"","Observacao":""},{"NumeroSequencial":"64","CodigoConsultora":"27253150","Previsao":"11 de outubro","Nome":"MARCIA FERREIRA CERQUEIRA","Rota":"0019","Semana":"","Observacao":""},{"NumeroSequencial":"65","CodigoConsultora":"27387207","Previsao":"11 de outubro","Nome":"CELINA APARECIDA DE SOUZA VIEIRA","Rota":"0019","Semana":"","Observacao":""},{"NumeroSequencial":"66","CodigoConsultora":"27059232","Previsao":"11 de outubro","Nome":"ANA PAULA IFANGER SOUZA","Rota":"0019","Semana":"","Observacao":""},{"NumeroSequencial":"67","CodigoConsultora":"27379223","Previsao":"11 de outubro","Nome":"ANA CLAUDIA MASAGAO DE PAULA GOMES","Rota":"0019","Semana":"","Observacao":""},{"NumeroSequencial":"68","CodigoConsultora":"30024083","Previsao":"11 de outubro","Nome":"MARIANE PEREIRA DE OLIVEIRA","Rota":"0019","Semana":"","Observacao":""},{"NumeroSequencial":"69","CodigoConsultora":"30128290","Previsao":"11 de outubro","Nome":"TANIA FERREIRA DA MOTA","Rota":"0019","Semana":"","Observacao":""},{"NumeroSequencial":"70","CodigoConsultora":"30140480","Previsao":"11 de outubro","Nome":"CASSILENE RODRIGUES CARDOSO","Rota":"0019","Semana":"","Observacao":""},{"NumeroSequencial":"71","CodigoConsultora":"30016621","Previsao":"11 de outubro","Nome":"ROBERTA TOKKO SAPOVICIS HEMMANN","Rota":"0019","Semana":"","Observacao":""},{"NumeroSequencial":"72","CodigoConsultora":"30007201","Previsao":"11 de outubro","Nome":"MARIA DA GLORIA MARTINS DE OLIVEIRA","Rota":"0019","Semana":"","Observacao":""},{"NumeroSequencial":"73","CodigoConsultora":"27367914","Previsao":"11 de outubro","Nome":"CHRISTIAN RODRIGUES SILVA","Rota":"0019","Semana":"","Observacao":""},{"NumeroSequencial":"74","CodigoConsultora":"27725691","Previsao":"11 de outubro","Nome":"POLLYANNA SANTIAGO DE CARVALHO","Rota":"0019","Semana":"","Observacao":""},{"NumeroSequencial":"75","CodigoConsultora":"27801169","Previsao":"11 de outubro","Nome":"CLAUDIA HELENA MAYER CRISTOFOLI","Rota":"0019","Semana":"","Observacao":""},{"NumeroSequencial":"76","CodigoConsultora":"27245930","Previsao":"11 de outubro","Nome":"LUCIMARA BITENCOURT DA SILVA","Rota":"0019","Semana":"","Observacao":""},{"NumeroSequencial":"77","CodigoConsultora":"30019279","Previsao":"11 de outubro","Nome":"MARLUCE ALVES DE OLIVEIRA","Rota":"0019","Semana":"","Observacao":""},{"NumeroSequencial":"78","CodigoConsultora":"30028569","Previsao":"11 de outubro","Nome":"KATIA MARIA FURLAN GODOY","Rota":"0019","Semana":"","Observacao":""},{"NumeroSequencial":"79","CodigoConsultora":"30014251","Previsao":"11 de outubro","Nome":"FERNANDO DE SOUZA CARDOSO","Rota":"0019","Semana":"","Observacao":""},{"NumeroSequencial":"80","CodigoConsultora":"30012996","Previsao":"11 de outubro","Nome":"EZILENE PINHEIRO DA ROCHA","Rota":"0019","Semana":"","Observacao":""},{"NumeroSequencial":"81","CodigoConsultora":"27718724","Previsao":"11 de outubro","Nome":"LENITA CASTILHO MOREIRA","Rota":"0019","Semana":"","Observacao":""},{"NumeroSequencial":"82","CodigoConsultora":"27712650","Previsao":"11 de outubro","Nome":"SILVANA MAIA","Rota":"0019","Semana":"","Observacao":""},{"NumeroSequencial":"83","CodigoConsultora":"30011691","Previsao":"11 de outubro","Nome":"LUANA CAVALCANTE DA SILVA","Rota":"0019","Semana":"","Observacao":""},{"NumeroSequencial":"84","CodigoConsultora":"27800672","Previsao":"11 de outubro","Nome":"IVANILZA FATIMA ROSA MARIA","Rota":"0019","Semana":"","Observacao":""},{"NumeroSequencial":"85","CodigoConsultora":"30155952","Previsao":"11 de outubro","Nome":"LIANE DE SOUZA SILVA","Rota":"0019","Semana":"","Observacao":""},{"NumeroSequencial":"86","CodigoConsultora":"30141096","Previsao":"11 de outubro","Nome":"MARIA CLAUDIA BARROSO COELHO","Rota":"0019","Semana":"","Observacao":""},{"NumeroSequencial":"87","CodigoConsultora":"27715343","Previsao":"11 de outubro","Nome":"SOLANGE DOS SANTOS PAULINO","Rota":"0019","Semana":"","Observacao":""},{"NumeroSequencial":"88","CodigoConsultora":"27717042","Previsao":"11 de outubro","Nome":"SINARA SILVA DOS SANTOS","Rota":"0019","Semana":"","Observacao":""},{"NumeroSequencial":"89","CodigoConsultora":"27635130","Previsao":"11 de outubro","Nome":"TEREZA DE SOUZA MACHADO BARBOSA","Rota":"0019","Semana":"","Observacao":""},{"NumeroSequencial":"90","CodigoConsultora":"27070701","Previsao":"11 de outubro","Nome":"REGIANE GOSER DE AZEVEDO","Rota":"0019","Semana":"","Observacao":""},{"NumeroSequencial":"91","CodigoConsultora":"27117246","Previsao":"11 de outubro","Nome":"SIRLEY ALVES MOREIRA","Rota":"0019","Semana":"","Observacao":""},{"NumeroSequencial":"92","CodigoConsultora":"30110874","Previsao":"11 de outubro","Nome":"DIOGO GABRIEL DE CARVALHO BARROS","Rota":"0019","Semana":"","Observacao":""}]}